{"name":"Pypassgen","tagline":"Python Password Generator - Generates strong passwords.","body":"PyPassGen Python Password Generator \r\n=========================================================================\r\n\r\nHey Friends, \r\nI strongly recommond ADMIN's using this because i see lot of admin:admin or password:password as login credentials ! \r\nSo sad, Giving the hacker a chance to hack your website using some lame security issue like BRUTEFORCE...\r\n\r\n=========================================================================\r\n\r\nUsage Instructions :- \r\n\r\nOn Windows :- \r\n-------------\r\n1) Enter this on the command line :- PyPassGen.py\r\n2) It will ask you to enter the number of charectars you want in the password.\r\n3) After entering the desired number of charectars , press enter \r\n4) You will see the generated password on the screen.\r\n\r\nOn Ubuntu :- \r\n-------------\r\n1) Enter this on the command line :- Python PyPassGen.py\r\n2) It will ask you to enter the number of charectars you want in the password.\r\n3) After entering the desired number of charectars , press enter \r\n4) You will see the generated password on the screen.\r\n\r\n\r\nHope you'll all will like it.\r\nAn queries ? Don't hesistate :) \r\n\r\n\r\n\r\n\r\n","google":"","note":"Don't delete this file! It's used internally to help with page regeneration."}